src/.pytest_cache/.gitignore
src/.pytest_cache/CACHEDIR.TAG
src/.pytest_cache/README.md
src/.pytest_cache/v/cache/lastfailed
src/.pytest_cache/v/cache/nodeids
src/.pytest_cache/v/cache/stepwise
src/__init__.py
src/adapters/__init__.py
src/adapters/redis_client.py
src/cli/__init__.py
src/cli/cli.py
src/cli/commands/__init__.py
src/cli/commands/add_task.py
src/cli/commands/config_redis.py
src/cli/commands/delete_task.py
src/cli/commands/get_by_priority.py
src/cli/commands/get_by_priority_range.py
src/cli/commands/list_tasks.py
src/cli/commands/update_task.py
src/cli/context.py
src/entities/__init__.py
src/entities/task.py
src/main.py
src/repositories/__init__.py
src/repositories/base_repository.py
src/repositories/fake_repository.py
src/repositories/redis_repository.py
src/services/__init__.py
src/services/task_service.py
src/utils/__init__.py
src/utils/config_handler.py
src/utils/emoji.py
src/utils/exceptions.py
luckytask-0.1.0.dist-info/METADATA
luckytask-0.1.0.dist-info/WHEEL
luckytask-0.1.0.dist-info/entry_points.txt
luckytask-0.1.0.dist-info/RECORD
