Metadata-Version: 2.1
Name: luckytask
Version: 0.1.0
Summary: Helps to manage your tasks
Author: oldcorvus
Author-email: moelcrow@gmail.com
Requires-Python: >=3.9,<4.0
Classifier: Programming Language :: Python :: 3
Classifier: Programming Language :: Python :: 3.9
Classifier: Programming Language :: Python :: 3.10
Classifier: Programming Language :: Python :: 3.11
Classifier: Programming Language :: Python :: 3.12
Requires-Dist: click (>=8.1.7,<9.0.0)
Requires-Dist: pre-commit (>=3.7.1,<4.0.0)
Requires-Dist: pydantic (>=2.7.4,<3.0.0)
Requires-Dist: redis (>=5.0.6,<6.0.0)
